[
  {
    "section": "SH1 Southern Motorway Cameras",
    "images": [
      {
        "title": "Spaghetti Junction (SH1/16 Port) – South",
        "src": "60.jpg"
      },
      {
        "title": "Market Road – South",
        "src": "225.jpg"
      },
      {
        "title": "Greenlane – North",
        "src": "80.jpg"
      },
      {
        "title": "SEART – South",
        "src": "90.jpg"
      },
      {
        "title": "Highbrook – North",
        "src": "110.jpg"
      },
      {
        "title": "Redoubt Road – North",
        "src": "100.jpg"
      },
      {
        "title": "SH1 & SH20 Interchange – North",
        "src": "214.jpg"
      },
      {
        "title": "Alfriston Road – North",
        "src": "120.jpg"
      },
      {
        "title": "Takanini – South",
        "src": "121.jpg"
      },
      {
        "title": "Walter Strevens – South",
        "src": "122.jpg"
      },
      {
        "title": "Pahurehure – South",
        "src": "123.jpg"
      },
      {
        "title": "Massey Road – North",
        "src": "290.jpg"
      },
      {
        "title": "Rushgreen – South",
        "src": "124.jpg"
      },
      {
        "title": "Park Estate – South",
        "src": "125.jpg"
      },
      {
        "title": "Slippery Creek – South",
        "src": "126.jpg"
      },
      {
        "title": "Ramarama – North",
        "src": "613.jpg"
      },
      {
        "title": "Bombay – North",
        "src": "610.jpg"
      },
      {
        "title": "Nikau – North",
        "src": "611.jpg"
      },
      {
        "title": "SH1/SH2 Interchange – North",
        "src": "612.jpg"
      }
    ]
  },
  {
    "section": "SH1 Northern Motorway Cameras",
    "images": [
      {
        "title": "Onewa – South",
        "src": "50.jpg"
      },
      {
        "title": "Esmonde – South",
        "src": "40.jpg"
      },
      {
        "title": "Northcote – North",
        "src": "30.jpg"
      },
      {
        "title": "Tristram – South",
        "src": "20.jpg"
      },
      {
        "title": "Greville – South",
        "src": "10.jpg"
      },
      {
        "title": "Dairy Flat – South",
        "src": "598.jpg"
      },
      {
        "title": "Wainui – South",
        "src": "651.jpg"
      },
      {
        "title": "Johnstone Hill Tunnels – South",
        "src": "215.jpg"
      }
    ]
  },
  {
    "section": "SH16 North Western Cameras",
    "images": [
      {
        "title": "Bond Street – West",
        "src": "130.jpg"
      },
      {
        "title": "Waterview Interchange – East",
        "src": "140.jpg"
      },
      {
        "title": "The Causeway – West",
        "src": "655.jpg"
      },
      {
        "title": "Te Atatu – East",
        "src": "150.jpg"
      },
      {
        "title": "Lincoln – East",
        "src": "160.jpg"
      },
      {
        "title": "Lincoln – West",
        "src": "170.jpg"
      },
      {
        "title": "Hobsonville Interchange – South",
        "src": "270.jpg"
      },
      {
        "title": "SH16 Extension – West",
        "src": "271.jpg"
      }
    ]
  },
  {
    "section": "SH20 South Western Cameras",
    "images": [
      {
        "title": "Waterview Tunnel entrance (City end) – South",
        "src": "669.jpg"
      },
      {
        "title": "Waterview Tunnel entrance (South end) – South",
        "src": "667.jpg"
      },
      {
        "title": "Richardson Road – South",
        "src": "668.jpg"
      },
      {
        "title": "Maioro – South",
        "src": "194.jpg"
      },
      {
        "title": "Dominion – South",
        "src": "193.jpg"
      },
      {
        "title": "Melrose – South",
        "src": "192.jpg"
      },
      {
        "title": "Hillsborough – South",
        "src": "191.jpg"
      },
      {
        "title": "Queenstown Road – North east",
        "src": "190.jpg"
      },
      {
        "title": "Onehunga Wharf – North",
        "src": "202.jpg"
      },
      {
        "title": "Rimu Road – North",
        "src": "203.jpg"
      }
    ]
  },
  {
    "section": "SH20a Airport Motorway Cameras",
    "images": [
      {
        "title": "Bader Drive – East",
        "src": "307.jpg"
      },
      {
        "title": "Kirkbride – North",
        "src": "275.jpg"
      },
      {
        "title": "Montgomerie – North",
        "src": "274.jpg"
      },
      {
        "title": "Puhinui – South",
        "src": "272.jpg"
      },
      {
        "title": "Selfs Road – North",
        "src": "288.jpg"
      },
      {
        "title": "Plunket Ave – East",
        "src": "208.jpg"
      },
      {
        "title": "Lambie Drive – East",
        "src": "209.jpg"
      },
      {
        "title": "SH20 to SH1 on–ramp – South",
        "src": "177.jpg"
      }
    ]
  },
  {
    "section": "SH18 Upper Harbour Motorway Cameras",
    "images": [
      {
        "title": "Paul Matthews – East",
        "src": "174.jpg"
      },
      {
        "title": "Albany Highway – East",
        "src": "172.jpg"
      },
      {
        "title": "Greenhithe Road – East",
        "src": "175.jpg"
      },
      {
        "title": "Tauhinu Interchange – East",
        "src": "171.jpg"
      },
      {
        "title": "Greenhithe Bridge – East",
        "src": "212.jpg"
      },
      {
        "title": "Sinton – West",
        "src": "224.jpg"
      },
      {
        "title": "Brigham Creek – East",
        "src": "223.jpg"
      },
      {
        "title": "Trig Road – West",
        "src": "221.jpg"
      }
    ]
  }
]
